{
  "id": "ch12-examples",
  "meta": {
    "title": "Lesson 12: もう昼ごはんを食べましたか — Dialogue & Examples",
    "subject": "japanese",
    "class": null,
    "lesson": "ch12-examples",
    "subtopic": "Already / Not Yet",
    "description": "Practical dialogues and sentences for Lesson 12: Already / Not Yet",
    "icon": "⌚",
    "difficulty": "beginner"
  },
  "teach": {
    "type": "flashcard",
    "items": [
      {
        "front": "もう vs まだ",
        "back": "もう + positive verb = already done\nもうたべました。= I already ate.\n\nまだ + 〜ていません = not yet\nまだたべていません。= I haven't eaten yet.\n\nKey: もう with positive past; まだ with 〜ていません!"
      },
      {
        "front": "〜ていません (not yet / haven't done)",
        "back": "て-form + いません = have not done\n(negative of て-form + います)\n\nまだたべていません。= Haven't eaten yet.\nまだかいていません。= Haven't written yet.\nまだよんでいません。= Haven't read yet.\n\nFor ongoing 'not yet' situations."
      },
      {
        "front": "Q&A: もう〜ましたか",
        "back": "Q: もう〜ましたか。= Have you already ~?\n\nA (yes): はい、もう〜ました。= Yes, already.\nA (not yet): いいえ、まだです。= No, not yet.\n   or: いいえ、まだ〜ていません。= No, haven't yet."
      },
      {
        "front": "〜てあります (done in preparation)",
        "back": "て-form + あります = has been done (in preparation)\n\nきっぷを買ってあります。\n= The ticket has been bought (in readiness).\n\nNote: てあります focuses on the resulting state,\noften implying someone did it intentionally."
      },
      {
        "front": "〜ておきます (do in advance)",
        "back": "て-form + おきます = do in advance / for a purpose\n\nパーティーの前にりょうりをしておきます。\n= I'll cook in advance of the party.\n\nImplication: doing now to be ready later."
      },
      {
        "front": "Common 'have you done' questions",
        "back": "もうしゅくだいをしましたか。= Have you done homework?\nもうレポートをかきましたか。= Have you written the report?\nもうばんごはんをたべましたか。= Have you eaten dinner?\n\nUse もう to ask if someone has ALREADY done something."
      }
    ]
  },
  "practice": {
    "gameType": "mcq-facts",
    "config": {
      "shuffleOptions": true,
      "timeLimit": 0,
      "questionsCount": 4
    },
    "items": [
      {
        "question": "You've already done your homework. How do you reply to もうしゅくだいをしましたか?",
        "answer": "はい、もうしました。",
        "options": [
          "はい、もうしました。",
          "いいえ、まだです。",
          "はい、まだしました。",
          "いいえ、もうしました。"
        ],
        "explanation": "はい + もう + ました = Yes, I've already done it."
      },
      {
        "question": "You haven't made a reservation yet. How do you say this?",
        "answer": "まだよやくをしていません。",
        "options": [
          "まだよやくをしていません。",
          "もうよやくをしていません。",
          "まだよやくをしました。",
          "もうよやくをしました。"
        ],
        "explanation": "まだ + 〜ていません = not yet done. よやく (予約) = reservation."
      },
      {
        "question": "Before a trip, you prepare clothes in advance. Which phrase describes this?",
        "answer": "ふくをじゅんびしておきます。",
        "options": [
          "ふくをじゅんびしておきます。",
          "ふくをじゅんびしてあります。",
          "ふくをじゅんびしています。",
          "ふくをじゅんびしてください。"
        ],
        "explanation": "〜ておきます = do in advance for future use. じゅんびしておきます = prepare in advance."
      },
      {
        "question": "The room has been cleaned (by someone, now it's ready). How do you say this?",
        "answer": "へやをそうじしてあります。",
        "options": [
          "へやをそうじしてあります。",
          "へやをそうじしています。",
          "へやをそうじしておきます。",
          "へやをそうじしてください。"
        ],
        "explanation": "〜てあります = has been done (resultant state, someone did it intentionally). そうじしてあります = has been cleaned."
      }
    ]
  },
  "challenge": {
    "gameType": "mcq-facts",
    "config": {
      "shuffleOptions": true,
      "timeLimit": 12,
      "questionsCount": 4
    },
    "items": [
      {
        "question": "You've already done your homework. How do you reply to もうしゅくだいをしましたか?",
        "answer": "はい、もうしました。",
        "options": [
          "はい、もうしました。",
          "いいえ、まだです。",
          "はい、まだしました。",
          "いいえ、もうしました。"
        ],
        "explanation": "はい + もう + ました = Yes, I've already done it."
      },
      {
        "question": "You haven't made a reservation yet. How do you say this?",
        "answer": "まだよやくをしていません。",
        "options": [
          "まだよやくをしていません。",
          "もうよやくをしていません。",
          "まだよやくをしました。",
          "もうよやくをしました。"
        ],
        "explanation": "まだ + 〜ていません = not yet done. よやく (予約) = reservation."
      },
      {
        "question": "Before a trip, you prepare clothes in advance. Which phrase describes this?",
        "answer": "ふくをじゅんびしておきます。",
        "options": [
          "ふくをじゅんびしておきます。",
          "ふくをじゅんびしてあります。",
          "ふくをじゅんびしています。",
          "ふくをじゅんびしてください。"
        ],
        "explanation": "〜ておきます = do in advance for future use. じゅんびしておきます = prepare in advance."
      },
      {
        "question": "The room has been cleaned (by someone, now it's ready). How do you say this?",
        "answer": "へやをそうじしてあります。",
        "options": [
          "へやをそうじしてあります。",
          "へやをそうじしています。",
          "へやをそうじしておきます。",
          "へやをそうじしてください。"
        ],
        "explanation": "〜てあります = has been done (resultant state, someone did it intentionally). そうじしてあります = has been cleaned."
      }
    ]
  }
}